powerline_owmweather/__init__.py
powerline_owmweather/weather.py
powerline_owmweather-0.5.dist-info/LICENSE
powerline_owmweather-0.5.dist-info/METADATA
powerline_owmweather-0.5.dist-info/WHEEL
powerline_owmweather-0.5.dist-info/top_level.txt
powerline_owmweather-0.5.dist-info/RECORD
